LICENSE
MANIFEST.in
README.md
__init__.py
__main__.py
entities.py
requirements.txt
setup.py
./LICENSE
./README.md
./__init__.py
./__main__.py
./entities.py
./mdparser.py
./requirements.txt
./test.py
plueprint.egg-info/PKG-INFO
plueprint.egg-info/SOURCES.txt
plueprint.egg-info/dependency_links.txt
plueprint.egg-info/requires.txt
plueprint.egg-info/top_level.txt